ALU_control.v
module alu_control (inst31_21, ALUOp, control_line);
	input[10:0] inst31_21;
	input[1:0] ALUOp;
	output reg[3:0]control_line;
	
	always begin 
		#1
		if ( ALUOp == 00) begin // LDUR & STUR
			control_line <= 4'b0010;
		end
		else if ( ALUOp == 01) begin
			control_line <= 4'b0111;
		end 
		else if (inst31_21 == 11001011000 && ALUOp == 10)begin //sub
			control_line <= 4'b0110;
		end 
		else if (inst31_21 == 10001010000 && ALUOp == 10)begin //and
			control_line <= 4'b0000;
		end 
		else if (inst31_21 == 10101010000 && ALUOp == 10)begin //orr
			control_line <= 4'b0001;
		end 
		else if (ALUOp == 10)begin //add, addi, branch, etc
			control_line <= 4'b0010;
		end
    end
	
endmodule

WriteBack.v
module WriteBack(Reg, loadedData, Results, MemToReg, RegWrite,
	  Data2Write, Reg2Write, oldRegWrite);

  input /*reg*/ [4:0] Reg;
  input /*reg*/ [63:0] loadedData, Results;
  input /*reg*/ MemToReg, RegWrite;
  output reg [63:0] Data2Write;
  output reg [4:0] Reg2Write;
  output reg oldRegWrite;

  always @(*)
  begin
	  #1
	  oldRegWrite <= RegWrite;
	  Reg2Write <= Reg;

	  if (MemToReg == 0)
		  Data2Write = Results;
	  else
		  Data2Write = loadedData;
	
  end
endmodule

MemoryAccess.v
`include "WriteBack.v"

module MemoryAccess(Instruction, branchAddress, Results, Data2, zero, B, BZ,
  	BNZ, MemRead, MemWrite, MemToReg, RegWrite, oldBranchAddress, PCSrc,
	oldRegWrite, Data2Write, Reg2Write);

  input /*reg*/ zero, B, BZ, BNZ, MemRead, MemWrite, MemToReg, RegWrite;
  input /*reg*/ [63:0] branchAddress, Results, Data2;
  input /*reg*/ [31:0] Instruction;
  output reg PCSrc;
	output reg [63:0] oldBranchAddress;
  reg [63:0] loadedData;
  output wire oldRegWrite;
  output wire [4:0] Reg2Write;
  output wire [63:0] Data2Write;

  reg [7:0] DMem[8191:0]; // 8192 bytes (1024 double words)

  
  initial // load  data memory
  begin 
	$readmemh("DM_Bytes.txt", DMem);
  end

  WriteBack wb(Instruction[4:0], loadedData, Results, MemToReg, RegWrite,
	  Data2Write, Reg2Write, oldRegWrite);

  always @(*)
  begin
	#1
	PCSrc = B | (BZ & zero) | (BNZ & ~zero);

	if (MemWrite == 1)
		DMem[Results] = Data2;
	if (MemRead == 1)
		loadedData = DMem[Results];

	oldBranchAddress = branchAddress;

  end
endmodule

Execution.v
`include "ALU_control.v"
`include "MemoryAccess.v"

module Execution(Address, Instruction, signExtInstr, Data1, Data2, ALUSrc,
	ALUOp, B, BZ, BNZ, MemWrite, MemRead, MemtoReg, RegWrite, Data2Write,
	Reg2Write, oldRegWrite, oldBranchAddress, PCSrc);

  input /*reg*/ [1:0] ALUSrc, ALUOp;
  input /*reg*/ B, BZ, BNZ, MemWrite, MemRead, MemtoReg, RegWrite;
  input /*reg*/ [31:0] Instruction;
  input /*reg*/ [63:0] Address, signExtInstr, Data1, Data2;
  reg [63:0] ALUInput2, branchAddress, Results;
  reg [3:0] ALUInstr;
  reg zero;
  output wire [4:0] Reg2Write;
  output wire PCSrc, oldRegWrite;
  output wire [63:0] oldBranchAddress, Data2Write;

  MemoryAccess mem(Instruction, branchAddress, Results, Data2, zero, B, BZ,
	BNZ, MemRead, MemWrite, MemToReg, RegWrite, oldBranchAddress, PCSrc,
	oldRegWrite, Data2Write, Reg2Write);

  alu_control aluControl(Instruction[31:21], ALUOp, ALUInst);

	always @(Instruction)
  begin
	#1
	branchAddress = Address + (signExtInstr << 2);

	case(ALUSrc)
		2'b00: ALUInput2 = Data2;
		2'b01: ALUInput2 = signExtInstr;
		2'b10: ALUInput2 = Instruction[21:10];
		default: $display("You messed up. ALUSrc sent invalid ",
			"Instr.\n");
	endcase

	case(ALUInst)
		4'b0000: Results = Data1 & ALUInput2;
		4'b0001: Results = Data1 | ALUInput2;
                4'b0010: Results = Data1 + ALUInput2;
                4'b0110: Results = Data1 - ALUInput2;
                4'b0111: Results = ALUInput2;
                4'b1100: Results = ~(Data1 | ALUInput2);
		default: $display("You messed up. ALUControl sent invalid ",
		       	"Instr.\n");
	endcase


	if (Results == 0)
		zero = 1;
	else
		zero = 0;
  end
endmodule

CPU_control.v

module cpu_control (inst31_21,Reg2Loc, Branch, BranchZero, BranchNonZero,
		    MemRead, MemtoReg, ALUOp, MemWrite, ALUSrc, RegWrite);
	input[10:0] inst31_21;
	output reg [1:0] ALUOp, ALUSrc;
	output reg Reg2Loc, Branch, BranchZero, BranchNonZero, MemRead, MemtoReg;
    	output reg MemWrite, RegWrite;
	
	/*wire [1:0] ALUOp, ALUSrc;
	wire Reg2Loc, Branch, BranchZero, BranchNonZero, MemRead, MemtoReg;
	wire MemWrite, RegWrite;*/
	
	
	always @ (inst31_21) begin 
		$display("\tCPU Control opcode: %11b \n", inst31_21);
		if 		(inst31_21 == 11'b11111000010) begin //LDUR 
				Reg2Loc <= 0; // ??
				Branch <= 0;
				BranchZero <= 0;
				BranchNonZero <= 0;
				MemRead <= 1;
				MemtoReg <= 1;
				ALUOp <= 2'b00;
				MemWrite <= 0;
				ALUSrc <= 2'b01;
				RegWrite <= 1;
		end
		else if (inst31_21 == 11'b11111000000) begin //STUR 
				Reg2Loc <= 1;
				Branch <= 0;
				BranchZero <= 0;
				BranchNonZero <= 0;
				MemRead <= 0;
				MemtoReg <= 0; // ??
				ALUOp <= 2'b00;
				MemWrite <= 1;
				ALUSrc <= 2'b01;
				RegWrite <= 0;
		end
		else if (inst31_21 == 11'b10001011000) begin //ADD 
				Reg2Loc <= 0;
				Branch <= 0;
				BranchZero <= 0;
				BranchNonZero <= 0;
				MemRead <= 0;
				MemtoReg <= 0; 
				ALUOp <= 2'b10;
				MemWrite <= 0;
				ALUSrc <= 2'b00;
				RegWrite <= 1;
		end
		else if (inst31_21[10:1] == 11'b1001000100) begin //ADDI 
				Reg2Loc <= 0;
				Branch <= 0;
				BranchZero <= 0;
				BranchNonZero <= 0;			
				MemRead <= 0;
				MemtoReg <= 0; 
				ALUOp <= 2'b10;
				MemWrite <= 0;
				ALUSrc <= 2'b10;
				RegWrite <= 1;
		end
		else if (inst31_21 == 11'b11001011000) begin //SUB
				Reg2Loc <= 0;
				Branch <= 0;
				BranchZero <= 0;
				BranchNonZero <= 0;
				MemRead <= 0;
				MemtoReg <= 0; 
				ALUOp <= 2'b10;
				MemWrite <= 0;
				ALUSrc <= 2'b00;
				RegWrite <= 1;
		end
		else if (inst31_21 == 11'b10001010000) begin //AND
				Reg2Loc <= 0;
				Branch <= 0;
				BranchZero <= 0;
				BranchNonZero <= 0;
				MemRead <= 0;
				MemtoReg <= 0; 
				ALUOp <= 2'b10;
				MemWrite <= 0;
				ALUSrc <= 2'b00;
				RegWrite <= 1;
		end
		else if (inst31_21 == 11'b10101010000 ) begin //ORR
				Reg2Loc <= 0;
				Branch <= 0;
				BranchZero <= 0;
				BranchNonZero <= 0;
				MemRead <= 0;
				MemtoReg <= 0; 
				ALUOp = 2'b10;
				MemWrite <= 0;
				ALUSrc <= 2'b00;
				RegWrite <= 1;
		end 
		else if (inst31_21[10:3] == 11'b10110100 ) begin //CBZ
				Reg2Loc <= 1;
				Branch <= 0;
				BranchZero <= 1;
				BranchNonZero <= 0;
				MemRead <= 0;
				MemtoReg <= 0; 
				ALUOp <= 2'b10;
				MemWrite <= 0;
				ALUSrc <= 2'b00;
				RegWrite <= 0;
		end 
		else if (inst31_21[10:3] == 11'b10110101 ) begin //CBNZ
				Reg2Loc <= 1;
				Branch <= 0;
				BranchZero <= 0;
				BranchNonZero <= 1;
				MemRead <= 0;
				MemtoReg <= 0; 
				ALUOp <= 2'b10;
				MemWrite <= 0;
				ALUSrc <= 2'b00;
				RegWrite <= 0;
		end 
		else if (inst31_21[10:5] == 11'b000101 ) begin //B
				Reg2Loc <= 0;
				Branch <= 1;
				BranchZero <= 0;
				BranchNonZero <= 0;
				MemRead <= 0;
				MemtoReg <= 0; 
				ALUOp <= 2'b10;
				MemWrite <= 0;
				ALUSrc <= 2'b00;
				RegWrite <= 0;
		end 
		else if (inst31_21 == 11'b11111111111 ) begin //HALT
				Reg2Loc <= 0;
				Branch <= 0;
				BranchZero <= 0;
				BranchNonZero <= 0;
				MemRead <= 0;
				MemtoReg <= 0; 
				ALUOp <= 2'b00;
				MemWrite <= 0;
				ALUSrc <= 2'b00;
				RegWrite <= 0;
		end 
		else begin
			$display("You messed up. Invalid opcode sent.\n");		
        	end	
	end 
endmodule

InstructionDecode.v
`include "Execution.v"
`include "CPU_control.v"

module InstructionDecode(Instruction, Address, PCSrc, BranchAddress);

  reg [63:0] Regs [31:0]; // 32 double words
  input /*reg*/ [31:0] Instruction;
  input /*reg*/ [63:0] Address;
  output PCSrc;
  output [63:0] BranchAddress;
  reg [63:0] Data1, Data2, signExtInstr;
  wire Reg2Loc, RegWrite, B, BZ, BNZ, MemRead, MemWrite, MemtoReg, PCSrc; 
  wire [1:0] ALUOp, ALUSrc;

  initial
  begin
	Regs[31] = {64{1'b0}};
  end

  cpu_control controlUnit(Instruction[31:21], Reg2Loc, B, BZ, BNZ,
	  MemRead, MemtoReg, ALUOp, MemWrite, ALUSrc, RegWrite);

  
  Execution ex(Address, Instruction, signExtInstr, Data1, Data2, ALUSrc,
	  ALUOp, B, BZ, BNZ, MemWrite, MemRead, MemtoReg, RegWrite,
	  Data2Write, Reg2Write, OldRegWrite, BranchAddress, PCSrc);
	
  always@(*)
  begin
	  #1
	  Data1 = Regs[Instruction[9:5]];

	  if (Reg2Loc == 0)
	          Data2 = Regs[Instruction[20:16]];
	  else
                  Data2[7:0] = Regs[Instruction[4:0]];

	  if(B)
	  begin
		  signExtInstr[25:0] = Instruction[25:0];
		  signExtInstr[63:45] = {38{Instruction[25]}};  
	  end
	  else if(BZ | BNZ)
	  begin		  
		  signExtInstr[18:0] = Instruction[23:5];
		  signExtInstr[63:45] = {45{Instruction[23]}};
	  end
	  else
	  begin
		  signExtInstr[9:0] = Instruction[20:11];
		  signExtInstr[63:10] = {54{Instruction[20]}};
	  end
	  $display("\tsignExtInstr: %64b ", signExtInstr);

  end
  always @(OldRegWrite)
  begin
	Regs[Reg2Write] = Data2Write;
  end
endmodule

InstructionFetch.v
/*
  Author: Prabakar, FIU-SCIS
   Template for proj4 test bench program
   Edited: Kevin Gonzalez, Dianaliz
*/

`include "InstructionDecode.v"

module InstructionFetch; // processor test bench template
  reg [7:0] IMem[4095:0]; // 4096 bytes (1024 words)
//  reg [7:0] DMem[8191:0]; // 8192 bytes (1024 double words)
  reg [31:0] instruction; // all instructions are 32-bit wide
  reg [63:0] PC; // PC contains 64-bit byte address
  integer i;
	
  initial // load instruction memory and data memory
  begin 
	$dumpfile("CPU.vcd");
	$dumpvars;
	$readmemh("IM_Bytes.txt", IMem);
//	$readmemh("DM_Bytes.txt", DMem);
	PC <= 64'b0; // initialize PC
	i = 0;
  end 
 
  InstructionDecode id(instruction, PC, PCSrc, BranchAddress);

  always //sequential logic of fetch for illustration
  begin
	#1
	  i = i + 1;
	// this code block can be performed in any other module
	// concatenate four bytes of IMem into PC
	  instruction[7:0] = IMem[PC];
	  instruction[15:8] = IMem[PC + 1];
	  instruction[23:16] = IMem[PC + 2];
	  instruction[31:24] = IMem[PC + 3];
	  $display("Opcode value: %32b %4d \n", instruction[31:0], i);
	  
	if (PCSrc == 0)
	begin
		PC = PC + 4; // PC needs to be updated in the processor/datapath module
	end
	else
	begin
		$display("\tBranchAddress: %64b", BranchAddress);
		PC = BranchAddress;
	end
  end

  // output data memory to a file when HALT instruction is fetched
  always @(instruction) 
  begin
	  if (instruction[31:21] == {11{1'b1}} | i == 30)
    begin
	$display("final opcode is detected \n");
//	$writememh("DM_Final_Bytes.txt", DMem);
	$finish;
    end
  end
endmodule

CPU.vcd
$date
	Tue Nov  6 19:52:03 2018
$end
$version
	Icarus Verilog
$end
$timescale
	1s
$end
$scope module InstructionFetch $end
$var wire 1 ! PCSrc $end
$var wire 1 " BranchAddress $end
$var reg 64 # PC [63:0] $end
$var reg 32 $ instruction [31:0] $end
$var integer 32 % i [31:0] $end
$scope module id $end
$var wire 64 & Address [63:0] $end
$var wire 32 ' Instruction [31:0] $end
$var wire 1 ( RegWrite $end
$var wire 1 ) Reg2Write $end
$var wire 1 * Reg2Loc $end
$var wire 1 ! PCSrc $end
$var wire 1 + OldRegWrite $end
$var wire 1 , MemtoReg $end
$var wire 1 - MemWrite $end
$var wire 1 . MemRead $end
$var wire 1 / Data2Write $end
$var wire 64 0 BranchAddress [63:0] $end
$var wire 1 1 BZ $end
$var wire 1 2 BNZ $end
$var wire 1 3 B $end
$var wire 2 4 ALUSrc [1:0] $end
$var wire 2 5 ALUOp [1:0] $end
$var reg 64 6 Data1 [63:0] $end
$var reg 64 7 Data2 [63:0] $end
$var reg 64 8 signExtInstr [63:0] $end
$scope module controlUnit $end
$var wire 11 9 inst31_21 [10:0] $end
$var reg 2 : ALUOp [1:0] $end
$var reg 2 ; ALUSrc [1:0] $end
$var reg 1 3 Branch $end
$var reg 1 2 BranchNonZero $end
$var reg 1 1 BranchZero $end
$var reg 1 . MemRead $end
$var reg 1 - MemWrite $end
$var reg 1 , MemtoReg $end
$var reg 1 * Reg2Loc $end
$var reg 1 ( RegWrite $end
$upscope $end
$scope module ex $end
$var wire 2 < ALUOp [1:0] $end
$var wire 2 = ALUSrc [1:0] $end
$var wire 64 > Address [63:0] $end
$var wire 1 3 B $end
$var wire 1 2 BNZ $end
$var wire 1 1 BZ $end
$var wire 64 ? Data1 [63:0] $end
$var wire 64 @ Data2 [63:0] $end
$var wire 32 A Instruction [31:0] $end
$var wire 1 . MemRead $end
$var wire 1 B MemToReg $end
$var wire 1 - MemWrite $end
$var wire 1 , MemtoReg $end
$var wire 1 ( RegWrite $end
$var wire 64 C signExtInstr [63:0] $end
$var wire 1 + oldRegWrite $end
$var wire 64 D oldBranchAddress [63:0] $end
$var wire 5 E Reg2Write [4:0] $end
$var wire 1 ! PCSrc $end
$var wire 64 F Data2Write [63:0] $end
$var wire 1 G ALUInst $end
$var reg 64 H ALUInput2 [63:0] $end
$var reg 64 I Results [63:0] $end
$var reg 64 J branchAddress [63:0] $end
$var reg 1 K zero $end
$scope module aluControl $end
$var wire 2 L ALUOp [1:0] $end
$var wire 11 M inst31_21 [10:0] $end
$var reg 4 N control_line [3:0] $end
$upscope $end
$scope module mem $end
$var wire 1 3 B $end
$var wire 1 2 BNZ $end
$var wire 1 1 BZ $end
$var wire 64 O Data2 [63:0] $end
$var wire 32 P Instruction [31:0] $end
$var wire 1 . MemRead $end
$var wire 1 B MemToReg $end
$var wire 1 - MemWrite $end
$var wire 1 ( RegWrite $end
$var wire 64 Q Results [63:0] $end
$var wire 64 R branchAddress [63:0] $end
$var wire 1 K zero $end
$var wire 1 + oldRegWrite $end
$var wire 5 S Reg2Write [4:0] $end
$var wire 64 T Data2Write [63:0] $end
$var reg 1 ! PCSrc $end
$var reg 64 U loadedData [63:0] $end
$var reg 64 V oldBranchAddress [63:0] $end
$scope module wb $end
$var wire 1 B MemToReg $end
$var wire 5 W Reg [4:0] $end
$var wire 1 ( RegWrite $end
$var wire 64 X Results [63:0] $end
$var wire 64 Y loadedData [63:0] $end
$var reg 64 Z Data2Write [63:0] $end
$var reg 5 [ Reg2Write [4:0] $end
$var reg 1 + oldRegWrite $end
$upscope $end
$upscope $end
$upscope $end
$upscope $end
$upscope $end
$enddefinitions $end
#0
$dumpvars
bx [
bx Z
bx Y
bx X
bx W
bx V
bx U
bx T
bx S
bx R
bx Q
bx P
bx O
bx N
bx M
bx L
xK
bx J
bx I
bx H
xG
bx F
bx E
bx D
bx C
zB
bx A
bx @
bx ?
b0 >
bx =
bx <
bx ;
bx :
bx 9
bx 8
bx 7
bx 6
bx 5
bx 4
x3
x2
x1
bx 0
x/
x.
x-
x,
x+
x*
x)
x(
bx '
b0 &
b0 %
bx $
b0 #
x"
x!
$end
#1
1(
b0 4
b0 ;
b0 =
0-
b10 5
b10 :
b10 <
b10 L
0,
0.
02
01
03
0*
b10001011000 9
b10001011000 M
b0 W
b10001011000111110000001111100000 $
b10001011000111110000001111100000 '
b10001011000111110000001111100000 A
b10001011000111110000001111100000 P
b1 %
#2
0)
b0 E
b0 S
b0 [
1+
b1111111111111111111111111111111111111111111111111111111111100000 8
b1111111111111111111111111111111111111111111111111111111111100000 C
b0 7
b0 @
b0 O
b0 6
b0 ?
#6
0!
#101
b100 #
b100 &
b100 >
#102
b1 4
b1 ;
b1 =
b0 5
b0 :
b0 <
b0 L
1,
1.
b11111000010 9
b11111000010 M
b10 W
b11111000010000000000000000000010 $
b11111000010000000000000000000010 '
b11111000010000000000000000000010 A
b11111000010000000000000000000010 P
b10 %
#103
b10 E
b10 S
b10 [
b0 8
b0 C
bx 7
bx @
bx O
bx 6
bx ?
#107
b0xxxxxxxx U
b0xxxxxxxx Y
#108
b0xxxxxxxx F
b0xxxxxxxx T
b0xxxxxxxx Z
#113
0G
b10 N
#114
1K
b0 I
b0 Q
b0 X
b0 H
b100 J
b100 R
#202
b1000 #
b1000 &
b1000 >
#203
b11 W
b11111000010000001000000000000011 $
b11111000010000001000000000000011 '
b11111000010000001000000000000011 A
b11111000010000001000000000000011 P
b11 %
#204
1)
b11 E
b11 S
b11 [
b10000 8
b10000 C
#208
0"
b100 0
b100 D
b100 V
b101 U
b101 Y
#209
1/
b101 F
b101 T
b101 Z
#303
b1100 #
b1100 &
b1100 >
#304
b111 W
b11111000010000010000000000000111 $
b11111000010000010000000000000111 '
b11111000010000010000000000000111 A
b11111000010000010000000000000111 P
b100 %
#305
b111 E
b111 S
b111 [
b100000 8
b100000 C
#404
b10000 #
b10000 &
b10000 >
#405
b0 4
b0 ;
b0 =
0,
0.
b10 5
b10 :
b10 <
b10 L
b10101010000 9
b10101010000 M
b100 W
b10101010000000100000000011100100 $
b10101010000000100000000011100100 '
b10101010000000100000000011100100 A
b10101010000000100000000011100100 P
b101 %
#406
0)
b100 E
b100 S
b100 [
b1000000 8
b1000000 C
#505
b10100 #
b10100 &
b10100 >
#506
b10001010000 9
b10001010000 M
b101 W
b10001010000001000000000001100101 $
b10001010000001000000000001100101 '
b10001010000001000000000001100101 A
b10001010000001000000000001100101 P
b110 %
#507
1)
b101 E
b101 S
b101 [
b10000000 8
b10000000 C
#606
b11000 #
b11000 &
b11000 >
#607
b10001011000 9
b10001011000 M
b10001011000001000000000010100101 $
b10001011000001000000000010100101 '
b10001011000001000000000010100101 A
b10001011000001000000000010100101 P
b111 %
#707
b11100 #
b11100 &
b11100 >
#708
b11001011000 9
b11001011000 M
b1000 W
b11001011000001110000000010101000 $
b11001011000001110000000010101000 '
b11001011000001110000000010101000 A
b11001011000001110000000010101000 P
b1000 %
#709
0)
b1000 E
b1000 S
b1000 [
b11100000 8
b11100000 C
#808
b100000 #
b100000 &
b100000 >
#809
0(
11
1*
b10110100000 9
b10110100000 M
b10110100000000000000000101101000 $
b10110100000000000000000101101000 '
b10110100000000000000000101101000 A
b10110100000000000000000101101000 P
b1001 %
#810
0+
b1011 8
b1011 C
#814
1!
#909
b0 #
b0 &
b0 >
#910
1(
01
0*
b10001011000 9
b10001011000 M
b0 W
b10001011000111110000001111100000 $
b10001011000111110000001111100000 '
b10001011000111110000001111100000 A
b10001011000111110000001111100000 P
b1010 %
#911
b0 E
b0 S
b0 [
1+
b1111111111111111111111111111111111111111111111111111111111100000 8
b1111111111111111111111111111111111111111111111111111111111100000 C
b0 7
b0 @
b0 O
b0 6
b0 ?
#915
0!
#1010
b100 #
b100 &
b100 >
#1011
b1 4
b1 ;
b1 =
b0 5
b0 :
b0 <
b0 L
1,
1.
b11111000010 9
b11111000010 M
b10 W
b11111000010000000000000000000010 $
b11111000010000000000000000000010 '
b11111000010000000000000000000010 A
b11111000010000000000000000000010 P
b1011 %
#1012
b10 E
b10 S
b10 [
b0 8
b0 C
b1 7
b1 @
b1 O
b1 6
b1 ?
#1111
b1000 #
b1000 &
b1000 >
#1112
b11 W
b11111000010000001000000000000011 $
b11111000010000001000000000000011 '
b11111000010000001000000000000011 A
b11111000010000001000000000000011 P
b1100 %
#1113
1)
b11 E
b11 S
b11 [
b10000 8
b10000 C
#1212
b1100 #
b1100 &
b1100 >
#1213
b111 W
b11111000010000010000000000000111 $
b11111000010000010000000000000111 '
b11111000010000010000000000000111 A
b11111000010000010000000000000111 P
b1101 %
#1214
b111 E
b111 S
b111 [
b100000 8
b100000 C
bx 7
bx @
bx O
#1313
b10000 #
b10000 &
b10000 >
#1314
b0 4
b0 ;
b0 =
0,
0.
b10 5
b10 :
b10 <
b10 L
b10101010000 9
b10101010000 M
b100 W
b10101010000000100000000011100100 $
b10101010000000100000000011100100 '
b10101010000000100000000011100100 A
b10101010000000100000000011100100 P
b1110 %
#1315
0)
b100 E
b100 S
b100 [
b1000000 8
b1000000 C
bx 6
bx ?
#1414
b10100 #
b10100 &
b10100 >
#1415
b10001010000 9
b10001010000 M
b101 W
b10001010000001000000000001100101 $
b10001010000001000000000001100101 '
b10001010000001000000000001100101 A
b10001010000001000000000001100101 P
b1111 %
#1416
1)
b101 E
b101 S
b101 [
b10000000 8
b10000000 C
#1515
b11000 #
b11000 &
b11000 >
#1516
b10001011000 9
b10001011000 M
b10001011000001000000000010100101 $
b10001011000001000000000010100101 '
b10001011000001000000000010100101 A
b10001011000001000000000010100101 P
b10000 %
#1616
b11100 #
b11100 &
b11100 >
#1617
b11001011000 9
b11001011000 M
b1000 W
b11001011000001110000000010101000 $
b11001011000001110000000010101000 '
b11001011000001110000000010101000 A
b11001011000001110000000010101000 P
b10001 %
#1618
0)
b1000 E
b1000 S
b1000 [
b11100000 8
b11100000 C
#1717
b100000 #
b100000 &
b100000 >
#1718
0(
11
1*
b10110100000 9
b10110100000 M
b10110100000000000000000101101000 $
b10110100000000000000000101101000 '
b10110100000000000000000101101000 A
b10110100000000000000000101101000 P
b10010 %
#1719
0+
b1011 8
b1011 C
#1723
1!
#1818
b0 #
b0 &
b0 >
#1819
1(
01
0*
b10001011000 9
b10001011000 M
b0 W
b10001011000111110000001111100000 $
b10001011000111110000001111100000 '
b10001011000111110000001111100000 A
b10001011000111110000001111100000 P
b10011 %
#1820
b0 E
b0 S
b0 [
1+
b1111111111111111111111111111111111111111111111111111111111100000 8
b1111111111111111111111111111111111111111111111111111111111100000 C
b0 7
b0 @
b0 O
b0 6
b0 ?
#1824
0!
#1919
b100 #
b100 &
b100 >
#1920
b1 4
b1 ;
b1 =
b0 5
b0 :
b0 <
b0 L
1,
1.
b11111000010 9
b11111000010 M
b10 W
b11111000010000000000000000000010 $
b11111000010000000000000000000010 '
b11111000010000000000000000000010 A
b11111000010000000000000000000010 P
b10100 %
#1921
b10 E
b10 S
b10 [
b0 8
b0 C
b1 7
b1 @
b1 O
b1 6
b1 ?
#2020
b1000 #
b1000 &
b1000 >
#2021
b11 W
b11111000010000001000000000000011 $
b11111000010000001000000000000011 '
b11111000010000001000000000000011 A
b11111000010000001000000000000011 P
b10101 %
#2022
1)
b11 E
b11 S
b11 [
b10000 8
b10000 C
#2121
b1100 #
b1100 &
b1100 >
#2122
b111 W
b11111000010000010000000000000111 $
b11111000010000010000000000000111 '
b11111000010000010000000000000111 A
b11111000010000010000000000000111 P
b10110 %
#2123
b111 E
b111 S
b111 [
b100000 8
b100000 C
bx 7
bx @
bx O
#2222
b10000 #
b10000 &
b10000 >
#2223
b0 4
b0 ;
b0 =
0,
0.
b10 5
b10 :
b10 <
b10 L
b10101010000 9
b10101010000 M
b100 W
b10101010000000100000000011100100 $
b10101010000000100000000011100100 '
b10101010000000100000000011100100 A
b10101010000000100000000011100100 P
b10111 %
#2224
0)
b100 E
b100 S
b100 [
b1000000 8
b1000000 C
bx 6
bx ?
#2323
b10100 #
b10100 &
b10100 >
#2324
b10001010000 9
b10001010000 M
b101 W
b10001010000001000000000001100101 $
b10001010000001000000000001100101 '
b10001010000001000000000001100101 A
b10001010000001000000000001100101 P
b11000 %
#2325
1)
b101 E
b101 S
b101 [
b10000000 8
b10000000 C
#2424
b11000 #
b11000 &
b11000 >
#2425
b10001011000 9
b10001011000 M
b10001011000001000000000010100101 $
b10001011000001000000000010100101 '
b10001011000001000000000010100101 A
b10001011000001000000000010100101 P
b11001 %
#2525
b11100 #
b11100 &
b11100 >
#2526
b11001011000 9
b11001011000 M
b1000 W
b11001011000001110000000010101000 $
b11001011000001110000000010101000 '
b11001011000001110000000010101000 A
b11001011000001110000000010101000 P
b11010 %
#2527
0)
b1000 E
b1000 S
b1000 [
b11100000 8
b11100000 C
#2626
b100000 #
b100000 &
b100000 >
#2627
0(
11
1*
b10110100000 9
b10110100000 M
b10110100000000000000000101101000 $
b10110100000000000000000101101000 '
b10110100000000000000000101101000 A
b10110100000000000000000101101000 P
b11011 %
#2628
0+
b1011 8
b1011 C
#2632
1!
#2727
b0 #
b0 &
b0 >
#2728
1(
01
0*
b10001011000 9
b10001011000 M
b0 W
b10001011000111110000001111100000 $
b10001011000111110000001111100000 '
b10001011000111110000001111100000 A
b10001011000111110000001111100000 P
b11100 %
#2729
b0 E
b0 S
b0 [
1+
b1111111111111111111111111111111111111111111111111111111111100000 8
b1111111111111111111111111111111111111111111111111111111111100000 C
b0 7
b0 @
b0 O
b0 6
b0 ?
#2733
0!
#2828
b100 #
b100 &
b100 >
#2829
b1 4
b1 ;
b1 =
b0 5
b0 :
b0 <
b0 L
1,
1.
b11111000010 9
b11111000010 M
b10 W
b11111000010000000000000000000010 $
b11111000010000000000000000000010 '
b11111000010000000000000000000010 A
b11111000010000000000000000000010 P
b11101 %
#2830
b10 E
b10 S
b10 [
b0 8
b0 C
b1 7
b1 @
b1 O
b1 6
b1 ?
#2929
b1000 #
b1000 &
b1000 >
#2930
b11 W
b11111000010000001000000000000011 $
b11111000010000001000000000000011 '
b11111000010000001000000000000011 A
b11111000010000001000000000000011 P
b11110 %
